pgeodistance/__init__.py
pgeodistance/pgeodistance.py
tests/__init__.py
pgeodistance-0.2.0.dist-info/LICENSE
pgeodistance-0.2.0.dist-info/METADATA
pgeodistance-0.2.0.dist-info/WHEEL
pgeodistance-0.2.0.dist-info/top_level.txt
pgeodistance-0.2.0.dist-info/RECORD
